papers/__init__.py
papers/_version.py
papers/bib.py
papers/config.py
papers/duplicate.py
papers/encoding.py
papers/extract.py
papers/latexenc.py
papers_fork-0.0.3.data/scripts/papers
papers_fork-0.0.3.dist-info/LICENSE
papers_fork-0.0.3.dist-info/METADATA
papers_fork-0.0.3.dist-info/WHEEL
papers_fork-0.0.3.dist-info/top_level.txt
papers_fork-0.0.3.dist-info/RECORD
